odoo/addons/purchase_variant_configurator/README.rst
odoo/addons/purchase_variant_configurator/__init__.py
odoo/addons/purchase_variant_configurator/__manifest__.py
odoo/addons/purchase_variant_configurator/hooks.py
odoo/addons/purchase_variant_configurator/i18n/es.po
odoo/addons/purchase_variant_configurator/i18n/es_AR.po
odoo/addons/purchase_variant_configurator/i18n/fr.po
odoo/addons/purchase_variant_configurator/i18n/hr.po
odoo/addons/purchase_variant_configurator/i18n/it.po
odoo/addons/purchase_variant_configurator/i18n/pt_BR.po
odoo/addons/purchase_variant_configurator/i18n/purchase_variant_configurator.pot
odoo/addons/purchase_variant_configurator/i18n/ro.po
odoo/addons/purchase_variant_configurator/i18n/sl.po
odoo/addons/purchase_variant_configurator/models/__init__.py
odoo/addons/purchase_variant_configurator/models/product_product.py
odoo/addons/purchase_variant_configurator/models/product_supplierinfo.py
odoo/addons/purchase_variant_configurator/models/product_template.py
odoo/addons/purchase_variant_configurator/models/purchase_order.py
odoo/addons/purchase_variant_configurator/models/res_company.py
odoo/addons/purchase_variant_configurator/models/res_config_settings.py
odoo/addons/purchase_variant_configurator/readme/CONFIGURE.md
odoo/addons/purchase_variant_configurator/readme/CONTRIBUTORS.md
odoo/addons/purchase_variant_configurator/readme/DESCRIPTION.md
odoo/addons/purchase_variant_configurator/readme/USAGE.md
odoo/addons/purchase_variant_configurator/static/description/icon.png
odoo/addons/purchase_variant_configurator/static/description/index.html
odoo/addons/purchase_variant_configurator/tests/__init__.py
odoo/addons/purchase_variant_configurator/tests/test_product_supplierinfo.py
odoo/addons/purchase_variant_configurator/tests/test_purchase_order.py
odoo/addons/purchase_variant_configurator/views/inherited_purchase_order_views.xml
odoo/addons/purchase_variant_configurator/views/res_config_settings_views.xml
odoo_addon_purchase_variant_configurator-17.0.1.0.1.dist-info/METADATA
odoo_addon_purchase_variant_configurator-17.0.1.0.1.dist-info/WHEEL
odoo_addon_purchase_variant_configurator-17.0.1.0.1.dist-info/top_level.txt
odoo_addon_purchase_variant_configurator-17.0.1.0.1.dist-info/RECORD
