Metadata-Version: 2.1
Name: odoo-addon-purchase_variant_configurator
Version: 17.0.1.0.1
Requires-Python: >=3.10
Requires-Dist: odoo-addon-product_variant_configurator>=17.0dev,<17.1dev
Requires-Dist: odoo>=17.0a,<17.1dev
Summary: Product variants in purchase management
Home-page: https://github.com/OCA/product-variant
License: AGPL-3
Author: AvanzOSC, Tecnativa, ACSONE SA/NV, Odoo Community Association (OCA)
Author-email: support@odoo-community.org
Classifier: Programming Language :: Python
Classifier: Framework :: Odoo
Classifier: Framework :: Odoo :: 17.0
Classifier: License :: OSI Approved :: GNU Affero General Public License v3
